{"additions": 15, "auther_ref": "Preparation_geant4_10.6", "auther_sha": "b1d2a8bfb5a40caae895cd9a31e2c369fe19809c", "author": "civanch", "body": "#### PR description:\r\nThis PR includes modifications which are needed to be integrated together with the migration of CMSSW to the new Geant4 version 10.6p01. So, only code checks are applided, no testing should be started.\r\n \r\n#### PR validation:\r\nprivate\r\n\r\n", "branch": "master", "changed_files": 4, "comments": 6, "commits": 3, "created_at": "1583171723", "deletions": 7, "labels": ["code-checks-approved", "comparison-pending", "hold", "orp-pending", "pending-signatures", "simulation-pending", "tests-pending"], "milestone": "CMSSW_11_1_X", "number": 29077, "release-notes": [], "review_comments": 0, "state": "open", "title": "Preparation for migration to Geant4 10.6", "updated_at": "1583172533", "user": "civanch"}