{"additions": 151, "auther_ref": "Phase2-hgx210", "auther_sha": "fb92f5206c84bf9cf93d4d12f07d39ead1d44d36", "author": "bsunanda", "body": "#### PR description:\r\n\r\nUpdate the cfi and cfg files with correct positions of the files and ERAs\r\n\r\n#### PR validation:\r\n\r\nPasses standard matrix tests\r\n\r\n#### if this PR is a backport please specify the original PR:\r\n\r\nNothing special", "branch": "master", "changed_files": 7, "comments": 1, "commits": 1, "created_at": "1565267829", "deletions": 9, "labels": ["code-checks-pending", "comparison-pending", "dqm-pending", "geometry-pending", "orp-pending", "pending-signatures", "tests-pending", "upgrade-pending"], "milestone": "CMSSW_11_0_X", "number": 27729, "release-notes": [], "review_comments": 0, "state": "open", "title": "Phase2-hgx210 Make may of the cfi files uptodate", "updated_at": "1565267864", "user": "bsunanda"}