{"additions": 49, "auther_ref": "TRKDQM_fixD0inMTV", "auther_sha": "2cdaab376585307ad940f008a30d808469bc1ccc", "author": "mtosi", "body": "#### PR description:\r\n\r\nadjust the impact parameter selection\r\nfor avoiding the 1st layer of the pixel detector (for phase1 : bug fix, for phase2 : new feature)\r\n\r\nthe efficiency plots produced by the MTV will be affected\r\nin the phase1, run3 and phase2_tracker era\r\n\r\n\r\nI have a question on the different eras in phase2\r\nthe MTV still makes use of either\r\nModifier_phase2_tracker_cff.py\r\nor\r\nModifier_phase2_timing_layer_cff.py\r\n\r\nshall we move to \r\nModifier_phase2_common_cff.py ?\r\n\r\n#### PR validation:\r\n`scram b runtests`\r\n`runTheMatrix.py -l limited -i all --ibeos` done\r\n\r\n", "branch": "master", "changed_files": 2, "comments": 1, "commits": 1, "created_at": "1557318219", "deletions": 4, "labels": ["code-checks-pending", "comparison-pending", "dqm-pending", "orp-pending", "pending-signatures", "tests-pending"], "milestone": "CMSSW_10_6_X", "number": 26700, "release-notes": [], "review_comments": 0, "state": "open", "title": "MTV : adjust impact parameter selection ", "updated_at": "1557318262", "user": "mtosi"}