{"additions": 719, "auther_ref": "Run3-hcx216", "auther_sha": "61c0c514e13a5f0d8bc1ec9cab32164bd38471b7", "author": "bsunanda", "body": "#### PR description:\r\n\r\nFirst step to utilize HcalSimulationParameters in the simulation software of HCAL. Some of the changes are withheld in view of conflicts with some unmerged PR's\r\n\r\n#### PR validation:\r\n\r\nTested with the standard workflows in the matrix\r\n\r\n#### if this PR is a backport please specify the original PR:\r\n\r\nNothing special", "branch": "master", "changed_files": 138, "comments": 36, "commits": 7, "created_at": "1565444754", "deletions": 821, "labels": ["code-checks-approved", "comparison-pending", "dqm-pending", "fastsim-pending", "geometry-pending", "orp-pending", "pending-signatures", "simulation-pending", "tests-approved", "upgrade-pending"], "milestone": "CMSSW_11_0_X", "number": 27743, "release-notes": [], "review_comments": 0, "state": "open", "title": "Run3-hcx216 allow to use HcalSimulationParameters", "updated_at": "1567279680", "user": "bsunanda"}