{"additions": 1222, "auther_ref": "PFClusterValidation", "auther_sha": "6d886d5f7b08efdabaf24b1e7e80d1e27574b512", "author": "akanugan", "body": "#### PR description:\r\n\r\n<! Added an analyzer to get  PFCluster summed energies ratio plots and some profile histograms. >\r\n\r\n#### PR validation:\r\n\r\n<!-- Added an analyzer to get PFCluster summed energies plots and some profile histograms. runTheMatrix test workflows. The plots produced locally good enough. Plugin, interface and cfg files are created. Finally, modified macro and .html files to get final set of plots   -->\r\n\r\n#### if this PR is a backport please specify the original PR:\r\n\r\nBefore submitting your pull requests, make sure you followed this checklist:\r\n- verify that the PR is really intended for the chosen branch\r\n- verify that changes follow [CMS Naming, Coding, And Style Rules](http://cms-sw.github.io/cms_coding_rules.html)\r\n- verify that the PR passes the basic test procedure suggested in the [CMSSW PR instructions](https://cms-sw.github.io/PRWorkflow.html)", "branch": "master", "changed_files": 8, "comments": 1, "commits": 5, "created_at": "1560531097", "deletions": 632, "labels": ["code-checks-pending", "comparison-pending", "dqm-pending", "orp-pending", "pending-signatures", "simulation-pending", "tests-pending"], "milestone": "CMSSW_11_0_X", "number": 27215, "release-notes": [], "review_comments": 0, "state": "open", "title": "Pf cluster validation", "updated_at": "1560531129", "user": "akanugan"}