{"additions": 90, "auther_ref": "Run3-alca158", "auther_sha": "75fcb34cea46e350b0c4dac2abd3014473fead7e", "author": "bsunanda", "body": "#### PR description:\r\n\r\nTry to improve PU effect on MIP signal for the front layers of HE to study radiation damage in scintillators\r\n\r\n#### PR validation:\r\n\r\nTested with 2018 data set\r\n\r\n#### if this PR is a backport please specify the original PR:\r\n\r\nNothing special", "branch": "master", "changed_files": 2, "comments": 10, "commits": 1, "created_at": "1566499579", "deletions": 15, "labels": ["alca-approved", "code-checks-approved", "comparison-available", "fully-signed", "orp-pending", "tests-approved"], "milestone": "CMSSW_11_0_X", "number": 27830, "release-notes": [], "review_comments": 0, "state": "open", "title": "Run3-alca158 Update the analysis macros for MIP monitoring of HE RadDam", "updated_at": "1566768694", "user": "bsunanda"}