{"additions": 0, "auther_ref": "revert-4753-vbfnlo_hjets", "auther_sha": "1438ae01f096f0dad1cb6375bb23f5522902477e", "author": "cms-sw", "body": "Reverts cms-sw/cmsdist#4753\r\n\r\nPending the fix preventing to build with gcc9", "branch": "IB/CMSSW_11_0_X/gcc700", "changed_files": 6, "comments": 11, "commits": 1, "created_at": "1560405854", "deletions": 103, "labels": ["comparison-available", "externals-pending", "orp-approved", "pending-signatures", "tests-approved"], "number": 5038, "release-notes": [], "review_comments": 0, "state": "open", "title": "Revert \"adding VBFNLO and Hjets++ to the externals linked to Herwig7\"", "updated_at": "1560447529", "user": "fabiocos"}