{"additions": 3, "auther_ref": "add-arch-and-branch-33", "auther_sha": "c276deba829582db6e0c8ffc01d0d44e6c339c75", "author": "mrodozov", "body": "Add two more fields", "branch": "V00-33-XX", "changed_files": 1, "comments": 1, "commits": 1, "created_at": "1579264659", "deletions": 1, "labels": ["comparison-pending", "externals-pending", "orp-pending", "pending-signatures", "tests-pending"], "number": 154, "release-notes": [], "review_comments": 0, "state": "open", "title": "Add arch and cmsdist branch to opts.json", "updated_at": "1579264688", "user": "mrodozov"}