{"additions": 2565, "auther_ref": "B", "auther_sha": "141482073645effd7c7abad4468f48ec52541d39", "author": "tschuh", "body": "#### PR description:\r\n\r\nNew EDProducer emulating the Stub processing of the Phase 2 Outer Tracker DTC boards and it's Product. The Pruduct has been added to the EventContent and the Producer to the StandardSequence as other Track Trigger modules which are already present.\r\n\r\n#### PR validation:\r\n\r\nbuild of DataFormats/L1TrackTrigger and L1Trigger/L1TTrackerDTC only\r\nrun of L1Trigger/L1TTrackerDTC/test/test_cfg.py\r\n\r\n#### Notes:\r\n\r\nI did not template the DTCProducer, it can handle only\r\nTTStub<edm::Ref<edm::DetSetVector<Phase2TrackerDigi>, Phase2TrackerDigi>>.\r\nI don't understand why TTStub and TTCluster are templated in first place.", "branch": "master", "changed_files": 27, "comments": 23, "commits": 3, "created_at": "1583747097", "deletions": 3, "labels": ["code-checks-approved", "comparison-pending", "l1-pending", "new-package-pending", "operations-pending", "orp-pending", "pending-signatures", "tests-pending", "upgrade-pending"], "milestone": "CMSSW_11_1_X", "number": 29151, "release-notes": [], "review_comments": 66, "state": "open", "title": "L1TTrackerDTC", "updated_at": "1584039624", "user": "tschuh"}