{"additions": 155, "auther_ref": "o2o-various-fixes-11X", "auther_sha": "5cd138e77f5043324220d9bd95cebcedaa1838c7", "author": "ggovi", "body": "#### PR description:\r\n- Clean up of python db credential management\r\n- Adaptation of existing O2O code for the above changes\r\n- Integration of deployment-related python code for ESGain O2O\r\n\r\n#### PR validation:\r\n\r\nUnit-tests + validation in online environment\r\n", "branch": "master", "changed_files": 38, "comments": 1, "commits": 2, "created_at": "1575449396", "deletions": 61, "labels": ["code-checks-pending", "comparison-pending", "db-pending", "orp-pending", "pending-signatures", "tests-pending"], "milestone": "CMSSW_11_1_X", "number": 28545, "release-notes": [], "review_comments": 0, "state": "open", "title": "Python code for ESGain O2O Deployment ", "updated_at": "1575449448", "user": "ggovi"}