{"additions": 8, "auther_ref": "root-openblas-fix", "auther_sha": "b8e41429adf789af505b6edc41646c03ff53bf6b", "author": "smuzaffar", "body": "Resolves https://github.com/cms-sw/cmsdist/pull/5528\r\n\r\nDrop unused specs\r\n-  photospline\r\n-  suitesparse\r\n\r\nand to make sure that we do not use lapack blas implementation we propose to drop it in favor of openblas.\r\n\r\nMove gslcblas library in to separate directory so that no one can link against it.", "branch": "IB/CMSSW_11_1_X/master", "changed_files": 8, "comments": 15, "commits": 4, "created_at": "1581493044", "deletions": 107, "labels": ["comparison-available", "externals-approved", "fully-signed", "orp-pending", "tests-rejected"], "number": 5540, "release-notes": [], "review_comments": 0, "state": "open", "title": "[11.1.X] Use OpenBlas instead of GSL Blas implementation", "updated_at": "1581543462", "user": "smuzaffar"}