{"additions": 131, "auther_ref": "switchProducerMassReplace", "auther_sha": "0b6bc439984fea342ec470f416755910b82a1178", "author": "makortel", "body": "#### PR description:\r\n\r\nThis PR fixes #28852. Before doing it, I took a round of traversing also untracked `PSet` and `VPSet` because I wanted to replace `pythonTypeName()` with `isinstance` for the type inspection.\r\n\r\nFor normal modules the `MassSearchReplaceParamVisitor` checks only the given parameter name, i.e. it does not descend into nested PSets. For `SwitchProducer` I **believe** the expected behavior would be to do the replacement for each contained `EDProducer`/`EDAlias`.\r\n\r\n#### PR validation:\r\n\r\nUnit tests run.", "branch": "master", "changed_files": 1, "comments": 17, "commits": 3, "created_at": "1581143556", "deletions": 24, "labels": ["code-checks-approved", "comparison-available", "core-pending", "orp-pending", "pending-signatures", "tests-approved"], "milestone": "CMSSW_11_1_X", "number": 28895, "release-notes": [], "review_comments": 0, "state": "open", "title": "Add support for untracked PSets and SwitchProducer to MassReplace tools", "updated_at": "1581167350", "user": "makortel"}