{"additions": 150, "auther_ref": "removePuppiPhoton", "auther_sha": "2337eb016bf910a3fb5f5f0372a301d7636f4a5d", "author": "ahinzmann", "body": "#### PR description:\r\n\r\nSimplify PUPPI MET computation, by removing (over-complicated) PUPPI photon algorithm and replace it by a simple option in PUPPI itself (avoid any kind of matching etc.).\r\nThe PR is supposed to keep tuning and physics of puppi (for jets) and puppiForMET untouched, however puppiNoLeptons (used for lepton isolation) is modified to include the same protection for high pT photons as puppiForMET.\r\n\r\n#### PR validation:\r\n\r\nChecked on 3000 QCD events that the high-pT photon candidates get the weight increased to 1 in old and new implementation.\r\nSmall differences arise when particle pt is close to the pT threshold of 20 within packedCandidate precision.\r\n\r\n@lathomas @zdemirag @abenecke @nhanvtran @violatingcp ", "branch": "master", "changed_files": 7, "comments": 58, "commits": 10, "created_at": "1567601988", "deletions": 151, "labels": ["analysis-pending", "code-checks-pending", "comparison-pending", "orp-pending", "pending-signatures", "reconstruction-pending", "tests-pending"], "milestone": "CMSSW_11_0_X", "number": 27929, "release-notes": [], "review_comments": 7, "state": "open", "title": "Simplify PUPPI Photon producer", "updated_at": "1570440667", "user": "ahinzmann"}